{
	"configurations" : 
	[
		{
			"directories" : 
			[
				{
					"build" : ".",
					"jsonFile" : "directory-.-Debug-f5ebdc15457944623624.json",
					"minimumCMakeVersion" : 
					{
						"string" : "3.10"
					},
					"projectIndex" : 0,
					"source" : ".",
					"targetIndexes" : 
					[
						0,
						1
					]
				}
			],
			"name" : "Debug",
			"projects" : 
			[
				{
					"directoryIndexes" : 
					[
						0
					],
					"name" : "flash_cache_CDN",
					"targetIndexes" : 
					[
						0,
						1
					]
				}
			],
			"targets" : 
			[
				{
					"directoryIndex" : 0,
					"id" : "flash_cache_CDN::@6890427a1f51a3e7e1df",
					"jsonFile" : "target-flash_cache_CDN-Debug-814a0b2b0634beddff32.json",
					"name" : "flash_cache_CDN",
					"projectIndex" : 0
				},
				{
					"directoryIndex" : 0,
					"id" : "run::@6890427a1f51a3e7e1df",
					"jsonFile" : "target-run-Debug-7f31c388bc2b290a3a2b.json",
					"name" : "run",
					"projectIndex" : 0
				}
			]
		}
	],
	"kind" : "codemodel",
	"paths" : 
	{
		"build" : "/home/laptop26/Documents/Retele/flash_cache_CDN/cmake-build-debug",
		"source" : "/home/laptop26/Documents/Retele/flash_cache_CDN"
	},
	"version" : 
	{
		"major" : 2,
		"minor" : 7
	}
}
